wecolib/__init__.py
wecolib/configs.txt
wecolib/wecolib.py
wecolib/wecolib_configs_and_tools.py
wecolib/wecolib_get_raw_data.py
wecolib/wecolib_indicators_and_editing_data.py
wecolib/wecolib_pattern_recognition_basic.py
wecolib/wecolib_pattern_recognition_recipe.py
wecolib/wecolib_quantitative_search.py
wecolib/wecolib_score_evaluation.py
wecolib/wecolib_simulation_box.py
wecolib/wecolib_trading_on.py
wecolib/wecolib_visualization.py
wecolib-1.0.7.dist-info/METADATA
wecolib-1.0.7.dist-info/WHEEL
wecolib-1.0.7.dist-info/top_level.txt
wecolib-1.0.7.dist-info/RECORD
